{
    "created_time": "2018-07-02T06:58:35Z",
    "files": [
        {
            "attachment_folder": "",
            "attachments": [
            ],
            "created_time": "2018-07-02T07:44:44Z",
            "modified_time": "2018-07-02T07:44:44Z",
            "name": "项目结构记录.md"
        },
        {
            "attachment_folder": "",
            "attachments": [
            ],
            "created_time": "2018-07-04T02:30:31Z",
            "modified_time": "2018-07-04T02:30:31Z",
            "name": "名词记录.md"
        },
        {
            "attachment_folder": "",
            "attachments": [
            ],
            "created_time": "2018-07-04T02:33:40Z",
            "modified_time": "2018-07-04T06:52:40Z",
            "name": "业务记录.md"
        },
        {
            "attachment_folder": "",
            "attachments": [
            ],
            "created_time": "2018-07-04T04:02:48Z",
            "modified_time": "2018-07-04T07:45:23Z",
            "name": "测试账户.md"
        },
        {
            "attachment_folder": "",
            "attachments": [
            ],
            "created_time": "2018-07-04T06:57:10Z",
            "modified_time": "2018-07-04T07:49:12Z",
            "name": "问题.md"
        },
        {
            "attachment_folder": "",
            "attachments": [
            ],
            "created_time": "2018-07-04T07:45:06Z",
            "modified_time": "2018-07-04T08:53:02Z",
            "name": "接口文档.md"
        },
        {
            "attachment_folder": "",
            "attachments": [
            ],
            "created_time": "2018-07-04T08:28:30Z",
            "modified_time": "2018-07-04T08:31:30Z",
            "name": "数据库表记录.md"
        }
    ],
    "sub_directories": [
    ],
    "version": "1"
}
