{
    "created_time": "2018-03-22T01:05:02Z",
    "files": [
        {
            "attachment_folder": "",
            "attachments": [
            ],
            "created_time": "2018-03-23T02:57:34Z",
            "modified_time": "2018-08-08T03:29:16Z",
            "name": "记录.md",
            "tags": [
            ]
        },
        {
            "attachment_folder": "",
            "attachments": [
            ],
            "created_time": "2018-03-23T02:57:38Z",
            "modified_time": "2018-03-23T02:57:38Z",
            "name": "问题.md",
            "tags": [
            ]
        }
    ],
    "sub_directories": [
    ],
    "version": "1"
}
